ldlm/__init__.py
ldlm/base_client.py
ldlm/client.py
ldlm/client_aio.py
ldlm/exceptions.py
ldlm/protos/__init__.py
ldlm/protos/ldlm_pb2.py
ldlm/protos/ldlm_pb2.pyi
ldlm/protos/ldlm_pb2_grpc.py
py_ldlm-1.1.3.dist-info/LICENSE
py_ldlm-1.1.3.dist-info/METADATA
py_ldlm-1.1.3.dist-info/WHEEL
py_ldlm-1.1.3.dist-info/top_level.txt
py_ldlm-1.1.3.dist-info/RECORD
