Metadata-Version: 2.2
Name: py-ldlm
Version: 1.1.3
Summary: LDLM client library
Author-email: Ian Moore <imoore76@yahoo.com>
License: 
Project-URL: Repository, https://github.com/imoore76/py-ldlm/
Project-URL: Documentation, https://github.com/imoore76/py-ldlm/README.md
Requires-Python: >=3.9
License-File: LICENSE
Requires-Dist: grpcio
Requires-Dist: google-api-python-client
Provides-Extra: test
Requires-Dist: pytest; extra == "test"
Requires-Dist: pytest-asyncio; extra == "test"
Requires-Dist: frozendict; extra == "test"
Requires-Dist: coverage; extra == "test"
Provides-Extra: docs
Requires-Dist: sphinx; extra == "docs"
Requires-Dist: sphinx_rtd_theme; extra == "docs"
Requires-Dist: autodoc; extra == "docs"
Requires-Dist: myst-parser; extra == "docs"
Requires-Dist: setuptools-scm>=8; extra == "docs"
Requires-Dist: m2r2; extra == "docs"
